BnLemma/RootWords_bnlemma_ekushey.yaml
BnLemma/SRA.py
BnLemma/__init__.py
BnLemma/edit_distance.py
BnLemma/iden.yaml
BnLemma/mapvg.txt
BnLemma/new.yaml
BnLemma/run.py
BnLemma/trie.py
BnLemma/word_lemma.py
BnLemma-2.1.dist-info/LICENSE
BnLemma-2.1.dist-info/METADATA
BnLemma-2.1.dist-info/WHEEL
BnLemma-2.1.dist-info/top_level.txt
BnLemma-2.1.dist-info/RECORD
