Metadata-Version: 2.1
Name: BnLemma
Version: 2.1
Summary: UNKNOWN
Home-page: https://github.com/Kowsher/Bangla-NLP/tree/master/Bangla%20Feature%20Extraction
Author: Karigor
Author-email: 
License: MIT
Platform: UNKNOWN
Classifier: Programming Language :: Python :: 3
Classifier: License :: OSI Approved :: MIT License
Classifier: Operating System :: OS Independent
